craigslist_watcher/__init__.py
craigslist_watcher/cli.py
craigslist_watcher/watcher.py
craigslist_watcher-0.1.1.dist-info/METADATA
craigslist_watcher-0.1.1.dist-info/RECORD
craigslist_watcher-0.1.1.dist-info/WHEEL
craigslist_watcher-0.1.1.dist-info/entry_points.txt
craigslist_watcher-0.1.1.dist-info/top_level.txt
