Metadata-Version: 2.1
Name: craigslist-watcher
Version: 0.1.1
Summary: Emails a list of urls to new posts found on craigslist page.
Home-page: https://github.com/alexseitsinger/craigslist_watcher
Author: Alex Seitsinger
Author-email: alexseitsinger@gmail.com
License: BSD 2-Clause License
Platform: UNKNOWN
Classifier: Development Status :: 3 - Alpha
Classifier: Intended Audience :: Developers
Classifier: Topic :: Utilities
Classifier: Programming Language :: Python
Classifier: Programming Language :: Python :: 3
Classifier: Programming Language :: Python :: 3.3
Classifier: Programming Language :: Python :: 3.4
Classifier: Programming Language :: Python :: 3.5
Classifier: Programming Language :: Python :: 3.6
Classifier: License :: OSI Approved :: BSD License
Requires-Dist: requests
Requires-Dist: bs4
Requires-Dist: maya
